app/__init__.py
app/ptm.py
app/templates/__init__.py
app/templates/python.gitignore
app/utils/__init__.py
app/utils/workspace.py
pytestmate-0.1.1.dist-info/licenses/LICENSE
pytestmate-0.1.1.dist-info/METADATA
pytestmate-0.1.1.dist-info/WHEEL
pytestmate-0.1.1.dist-info/entry_points.txt
pytestmate-0.1.1.dist-info/top_level.txt
pytestmate-0.1.1.dist-info/RECORD
