Metadata-Version: 2.4
Name: pytestmate
Version: 0.1.1
Summary: Generate Pytests for your project through the terminal.
Requires-Python: >=3.11
License-File: LICENSE
Requires-Dist: click>=8.1.8
Requires-Dist: pathspec>=0.12.1
Requires-Dist: pytest>=8.3.5
Dynamic: license-file
